Workbook

Sheet Cover
A1: Cover
O5: #003e83
O6: #0085f0
O7: #2cdcff
D12: Project Management Plan
E16: Projec Code | F16: [Project Code] | H16: System ID | I16: [System ID]
E17: Project Name | F17: [Project Name] | H17: System Name | I17: [System Name]
E18: Project Manager | F18: [Project Manager] | H18: Updated Date | I18: [Updated Date]
F21: PM | G21: BU Review | H21: Sale review | I21: Approve
E22: Name | F22: [Name of PM] | G22: [Name of reviewer] | H22: [Name of reviewer] | I22: [Name of approver]
E23: Role | F23: PM | G23: BU Leader | H23: Sale Leader | I23: [Role of approver]
E24: Date | F24: [Created Date] | G24: [Review Date] | H24: [Review Date] | I24: [Approve date]

Sheet Page Revision History
D1: REVISION HISTORY | L1: Mã số: BM03-QT-OP-01
L2: Ngày hiệu lực: 10/09/2025
L3: Lần ban hành: 02
B6: # | C6: Last Edited Date | D6: Change Details | G6: Reason | H6: Version | J6: Creator by | K6: Approver by | L6: Remark
B7: 1 | C7: 45661 | D7: Tạo mới | G7: Tạo mới | H7: 1.0 | J7: KhanhPN | K7: DuyTQ
B8: 2 | C8: 45939 | D8: Cập nhật phạm vi áp dụng | G8: Sửa đổi | H8: 2.0 | J8: KhanhPN | K8: DuyTQ
B9: 3
B10: 4
B11: 5
B12: 6
B13: 7
B14: 8
B15: 9
B16: 10
B17: 11
B18: 12
B19: 13
B20: 14
B21: 15

Sheet 0. Tasklist
D1: Project Plan Task List | G1: ='Page Revision History'!L1 -> Mã số: BM03-QT-OP-01
G2: ='Page Revision History'!L2 -> Ngày hiệu lực: 10/09/2025
G3: ='Page Revision History'!L3 -> Lần ban hành: 02
B5: No | C5: Task | D5: PIC | E5: Purpose | F5: Note | H5: Status
B6: 1 | C6: 1. Project Information | D6: PM | E6: 1. Project Information 2. Project Scope 3. Project deliverales 4. Project milestone | H6: Open
B7: 2 | C7: 2. Role & Team | D7: PM | E7: 1. Project Roles 2. Responsibility Matrix (RACI Matrix) 3. Team | H7: Open
B8: 3 | C8: 3.Configuration Plan | D8: PM | E8: 1. Folder Configuration/Folder Structure 2. File/Document Configuration 3. Source Code Management 4. Environement Control 5. Other Configuration | H8: Open
B9: 4 | C9: 4. Communication Plan & Tools | D9: PM | E9: 1. Meeting Plan 2. Communication plan 3. Comunication Tools 4. Development Tools | H9: Open
B10: 5 | C10: 5. Standard Metric | D10: PM | E10: 1. Standard metric 2. Quality metric by Stage 3. Quality Assurance Strategic 3. Non-functional requirements ensuring criteria | H10: Open
B11: 6 | C11: 6. Other Plan | D11: PM | E11: 1. Change Management 2. Risk Management​ 3. Resource Allocation Plan | F11: Chủ yếu refer các tài liệu khác | H11: Open

Sheet 1. Project Information
D1: Project Information | F1: ='0. Tasklist'!$G$1 -> Mã số: BM03-QT-OP-01
F2: ='0. Tasklist'!$G$2 -> Ngày hiệu lực: 10/09/2025
F3: ='0. Tasklist'!$G$3 -> Lần ban hành: 02
B5: Project Code | D5: [Enter Project Code] | F5: Project Manager | G5: [Enter Project Manager]
B6: Project Name | D6: [Enter Project Name] | F6: Updated Date | G6: [Enter Updated Date]
B8: 1. Project Information
B9: Project Customer | D9: Customer Code | F9: Customer Name
B10: Project Type | D10: Contract Type | E10: Fixed Price | F10: Project Type | G10: New Development
B11: Project Period | D11: Start Date | E11: YYYY-MM-DD | F11: End Date | G11: YYYY-MM-DD
B12: Project Effort (Man month) | D12: Budgeted Plan | F12: Plan Effort
B13: Project Overview | D13: Project Situation | E13: [Mô tả về bối cảnh dự án, các nhu cầu tư đâu mà phát sinh ra dự án. + Yêu cầu từ quy trình công việc + Yêu cầu từ người dùng cuối hay khách hang của khách hang + Yêu câu từ hiệu suất hoặc hiệu quả của hệ thống hiện tại. ]
D14: Project Product | E14: [Project product overview: Mô tả overview về hệ thống hoặc dịch vụ mà dự án sẽ phát triển/triển khai hoặc bàn giao cho khách hàng. Product description: Mô tả về các chức năng chính, các kết quả chính mà sản phẩm hoặc dịch vụ của dự án sẽ bao gồm hoặc sẽ cung cấp. Ví dụ: + Quản lý người dùng + Quản lý sản phẩm + Quản lý giao dịch Product technical description: Mô tả overview thông số kỹ thuật nếu có về sản phẩm ]
B15: Project's Acceptance Criteria | D15: Criteria | E15: Description | F15: Acceptance Criteria
D16: 1
D17: 2
D18: 3
D19: 4
D20: 5
B22: 2. Project Scope
B23: 2.1. Project Stage
B24: No | C24: Stage | D24: Customer | E24: Internal
B25: 1 | C25: Requirement Gathering | D25: Yes | E25: Yes
B26: 2 | C26: System Analysis | D26: Yes | E26: Yes
B27: 3 | C27: UI/UX Design | D27: Yes | E27: Yes
B28: 4 | C28: Architecture Design | D28: No | E28: Yes
B29: 5 | C29: Detail Design | D29: Yes | E29: Yes
B30: 6 | C30: Coding | D30: No | E30: Yes
B31: 7 | C31: Testing | D31: Yes | E31: Yes
B32: 8 | C32: Deployment | D32: Yes | E32: Yes
B33: 9 | C33: Maintenance | D33: Yes | E33: Yes
B35: 2.2. Project Environment
B36: No | C36: Environment | D36: Yes/No
B37: 1 | C37: Development Environment | D37: Yes
B38: 2 | C38: Testing Environment | D38: Yes
B39: 3 | C39: Staging Environment | D39: Yes
B40: 4 | C40: Production Environment | D40: Yes
B42: 2.3. Project Technologies
B43: No | C43: Component | D43: Description
B44: 1 | C44: Mobile App | D44: Flutter vx.y
B45: 2 | C45: Web | D45: ReactJS vx.y
B46: 3 | C46: Deployment Platform | D46: Amazon Web service
B47: 4
B49: 3. Project deliverales
B50: No | C50: Deliverables | D50: Deliverables' Acceptance Criteria | F50: Stage | G50: Status
B51: 1 | C51: Tài liệu thiết kế hệ thống | F51: Architecture Design | G51: Done
B52: 2 | G52: Done
B53: 3 | G53: Done
B54: 4 | G54: Done
B55: 5 | G55: Done
B57: 4. Project milestone
B58: No | C58: Milestone | D58: Description | F58: Plan schedule | G58: Actual schedule | H58: Status
B59: 1 | F59: [YYYY-MM-DD]-[YYYY-MM-DD] | G59: [YYYY-MM-DD]-[YYYY-MM-DD] | H59: Done
B60: 2 | F60: [YYYY-MM-DD]-[YYYY-MM-DD] | G60: [YYYY-MM-DD]-[YYYY-MM-DD] | H60: Done
B61: 3 | F61: [YYYY-MM-DD]-[YYYY-MM-DD] | G61: [YYYY-MM-DD]-[YYYY-MM-DD] | H61: Done
B62: 4 | F62: [YYYY-MM-DD]-[YYYY-MM-DD] | G62: [YYYY-MM-DD]-[YYYY-MM-DD] | H62: Done
B63: 5 | F63: [YYYY-MM-DD]-[YYYY-MM-DD] | G63: [YYYY-MM-DD]-[YYYY-MM-DD] | H63: Done
B65: 4. Project Review Plan/Retro Meeting Plan
B66: No | C66: Review Milestone | D66: Description | F66: Plan schedule | G66: Actual schedule | H66: Status
B67: 1 | F67: [YYYY-MM-DD]-[YYYY-MM-DD] | G67: [YYYY-MM-DD]-[YYYY-MM-DD] | H67: Done
B68: 2 | F68: [YYYY-MM-DD]-[YYYY-MM-DD] | G68: [YYYY-MM-DD]-[YYYY-MM-DD] | H68: Done
B69: 3 | F69: [YYYY-MM-DD]-[YYYY-MM-DD] | G69: [YYYY-MM-DD]-[YYYY-MM-DD] | H69: Done
B70: 4 | F70: [YYYY-MM-DD]-[YYYY-MM-DD] | G70: [YYYY-MM-DD]-[YYYY-MM-DD] | H70: Done
B71: 5 | F71: [YYYY-MM-DD]-[YYYY-MM-DD] | G71: [YYYY-MM-DD]-[YYYY-MM-DD] | H71: Done
B73: 5. Yêu cầu bảo mật
B74: No | C74: Component | D74: Description | F74: Stage | G74: Status
B75: 1 | C75: Xác thực người dùng | D75: Hệ thống phải đảm bảo xác thực người dùng bằng mật khẩu mạnh, OTP hoặc MFA. | F75: Architecture Design | G75: Done
B76: 2 | C76: Phân quyền truy cập | D76: Chỉ người dùng có vai trò phù hợp mới được phép truy cập vào dữ liệu nhạy cảm. | F76: Detail Design | G76: Done
B77: 3 | C77: Mã hóa dữ liệu | D77: Dữ liệu phải được mã hóa khi lưu trữ (AES-256) và truyền tải (TLS 1.2+). | F77: Coding | G77: Done
B78: 4 | C78: Ghi nhật ký (Audit log) | D78: Ghi lại các hành động quan trọng: đăng nhập, sửa/xóa dữ liệu, phân quyền,... | F78: Coding | G78: Done
B79: 5 | C79: Quản lý lỗ hổng | D79: Thường xuyên rà soát, đánh giá và cập nhật các bản vá bảo mật kịp thời. | F79: Maintenance | G79: Done
B81: 6. Yêu cầu bảo vệ dữ liệu cá nhân
B82: Dự án có triển khai nội dung liên quan đến việc xử lý dữ liệu cá nhân thì điền vào table bên dưới
B83: No | C83: Component | D83: Description | F83: Stage | G83: Status
B84: 1 | C84: Thu thập tối thiểu (Data Minimization) | D84: Chỉ thu thập những thông tin cần thiết cho mục đích đã xác định, không dư thừa. | F84: Architecture Design | G84: Done
B85: 2 | C85: Mã hóa dữ liệu cá nhân | D85: Dữ liệu như tên, số điện thoại, CCCD, địa chỉ,… phải được mã hóa hoặc làm ẩn danh (anonymization). | F85: Coding | G85: Done
B86: 3 | C86: Chính sách lưu trữ & xóa dữ liệu | D86: Thiết lập thời gian lưu trữ hợp lý, có cơ chế tự động xóa hoặc yêu cầu xóa theo yêu cầu người dùng. | F86: Coding | G86: Done
B87: 4 | C87: Giao diện quản lý quyền riêng tư | D87: Cho phép người dùng truy cập, chỉnh sửa, hoặc yêu cầu xóa dữ liệu của họ theo luật định. | F87: Detail Design | G87: Done
B88: 5 | C88: Tuân thủ pháp lý | D88: Hệ thống cần tuân thủ các quy định như: GDPR, Nghị định 13/2023/NĐ-CP (VN),... | F88: All | G88: Done

Sheet 2. Role & Team
D1: Role & Team | J1: ='0. Tasklist'!$G$1 -> Mã số: BM03-QT-OP-01
J2: ='0. Tasklist'!$G$2 -> Ngày hiệu lực: 10/09/2025
J3: ='0. Tasklist'!$G$3 -> Lần ban hành: 02
B5: 1. Project Roles
B6: No | C6: Role | D6: Abbreviation | E6: Type | F6: Responsibility Description
B7: 1 | C7: Project Manager | D7: PM | E7: Internal | F7: [Fill responibilities of this role]
B8: 2 | C8: Solution Architecturer | D8: SA | E8: Internal | F8: [Fill responibilities of this role]
B9: 3 | C9: Technical Leader | D9: TL | E9: Internal | F9: [Fill responibilities of this role]
B10: 4 | C10: Developer | D10: DEV | E10: Internal | F10: [Fill responibilities of this role]
B11: 5 | C11: Tester | D11: TEST | E11: Internal | F11: [Fill responibilities of this role]
B12: 6 | C12: Designer | D12: DESIGNER | E12: Internal | F12: [Fill responibilities of this role]
B13: 7 | C13: Comtor | D13: COMTOR | E13: Internal | F13: [Fill responibilities of this role]
B14: 8 | C14: Customer | D14: CUSTOMER | E14: External | F14: [Fill responibilities of this role]
B15: 9
B16: 10
B17: 11
B19: 2. Responsibility Matrix (RACI Matrix)
H20: Role
B21: No | C21: Task/Activity | D21: Stage | E21: Project Manager | F21: Solution Architecturer | G21: Technical Leader | H21: Developer | I21: Tester | J21: Designer | K21: Customer
B22: 1 | C22: Architecture Design | D22: Architecture Design | E22: A | F22: R | G22: C | H22: I | I22: I | J22: I | K22: I
B23: 2 | C23: Detail Design | D23: Detail Design | E23: A | F23: C | G23: R | H23: I | I23: I | J23: I | K23: I
B24: 3 | C24: Test Case | D24: Testing | E24: A | F24: I | G24: I | H24: I | I24: R | J24: I | K24: I
B25: 4
B26: 5
B27: 6
B28: 7
B29: 8
B30: 9
B31: 10
B33: 3. Team
B34: No | C34: Name | D34: Role | E34: Email | F34: Joined Date | G34: Released Date | H34: Phone | I34: Type
B35: 1 | C35: Nguyễn Văn A1 | D35: Project Manager | F35: 45658 | G35: 46022 | I35: Internal
B36: 2 | C36: Nguyễn Văn A2 | D36: Solution Architecturer | F36: 45658 | G36: 46022 | I36: Internal
B37: 3 | C37: Nguyễn Văn A3 | D37: Technical Leader | F37: 45658 | G37: 46022 | I37: Internal
B38: 4 | C38: Nguyễn Văn A4 | D38: Developer | F38: 45658 | G38: 46022 | I38: Internal
B39: 5 | C39: Nguyễn Văn A5 | D39: Developer | F39: 45658 | G39: 46022 | I39: Internal
B40: 6 | C40: Nguyễn Văn A6 | D40: Tester | F40: 45658 | G40: 46022 | I40: Internal
B41: 7 | C41: Nguyễn Văn A7 | D41: Tester | F41: 45658 | G41: 46022 | I41: Internal
B42: 8 | C42: Nguyễn Văn A8 | D42: Designer | F42: 45658 | G42: 46022 | I42: Internal
B43: 9 | C43: Nguyễn Văn A9 | D43: Comtor | F43: 45658 | G43: 46022 | I43: Internal
B44: 10 | C44: Nguyễn Văn A10 | D44: Customer | F44: 45658 | G44: 46022 | I44: External

Sheet 3.Configuration Plan
D1: Configuration Plan | G1: ='0. Tasklist'!$G$1 -> Mã số: BM03-QT-OP-01
G2: ='0. Tasklist'!$G$2 -> Ngày hiệu lực: 10/09/2025
G3: ='0. Tasklist'!$G$3 -> Lần ban hành: 02
B6: No | C6: Folder | D6: Description | F6: Location | G6: Access Permission | H6: Location Type (Teams/NextCloud/ … ) | I6: Link
B7: =ROW()-6 -> 1 | C7: Root Folder: [Project Code] | D7: Project Lead channel in Teams | F7: /[ProjectCode] | H7: Teams
B8: =ROW()-6 -> 2 | C8: 01_Project_Planning | D8: (Project Open, Contract, Estimation) BM01, BM02 | F8: /[ProjectCode] | G8: Read: BUL, PM, Sales Write/Modify: BUL, PM, Sales Delete: BUL, PM, Sales | H8: Teams
B9: =ROW()-6 -> 3 | C9: Root Folder: [Project Code] | D9: Project Team channel in Teams | F9: /[ProjectCode] | H9: Teams
B10: =ROW()-6 -> 4 | C10: 01_Project_Planning | D10: (Project management plan, schedules, risk assessments, project reports) BM03 , BM04 , BM05, BM07, BM09, BM10, BM12,BM32, BM33 | F10: /[ProjectCode]/01_Project_Planning | G10: Read: All members Write/Modify: PM, TL Delete: PM | H10: Teams
B11: =ROW()-6 -> 5 | C11: 02_Requirements | D11: (Business and technical requirements, change requests) BM06, BM13, BM14, BM15, BM34 | F11: /[ProjectCode]/02_Requirements | G11: Read: All members Write/Modify: PM, TL Delete: PM | H11: Teams
B12: =ROW()-6 -> 6 | C12: 03_Design | D12: (Wireframes, architecture diagrams, UI/UX design, detail design) BM18, BM19, BM20, BM21, BM22, BM23 | F12: /[ProjectCode]/03_Design | G12: Read: All members Write/Modify: PM, TL, Designer Delete: PM | H12: Teams
B13: =ROW()-6 -> 7 | C13: 04_Development | D13: (Source code, scripts, database schemas) BM24 | F13: /[ProjectCode]/04_Development | G13: Read: All members Write/Modify: PM, TL, Developer Delete: PM | H13: Teams
B14: =ROW()-6 -> 8 | C14: 05_Testing | D14: (Test cases, Test results, Test report) BM26, BM27, BM28, BM29 | F14: /[ProjectCode]/05_Testing | G14: Read: All members Write/Modify: PM, TL, Tester Delete: PM | H14: Teams
B15: =ROW()-6 -> 9 | C15: 06_Deployment | D15: (Release notes, deployment scripts, rollback plans) BM30, BM31 | F15: /[ProjectCode]/06_Deployment | G15: Read: All members Write/Modify: PM, TL, Tester Delete: PM | H15: Teams
B16: =ROW()-6 -> 10 | C16: 07_Documentation | D16: (User manuals, training guides, FAQs and project templates) | F16: /[ProjectCode]/07_Documentation | G16: Read: All members Write/Modify: All members Delete: PM | H16: Teams
B17: =ROW()-6 -> 11 | C17: 08_Communication | D17: (Meeting minutes, emails, stakeholder reports) BM08 | F17: /[ProjectCode]/08_Communication | G17: Read: All members Write/Modify: PM, TL Delete: PM | H17: Teams
B18: =ROW()-6 -> 12 | C18: 09_Backups | D18: (Versioned backups, recovery plans) | F18: /[ProjectCode]/09_Backups | G18: Read: All members Write/Modify: PM, TL Delete: PM | H18: Teams
B19: =ROW()-6 -> 13 | C19: 10_CustomerSupplied | D19: (All materials provided by Customer) | F19: /[ProjectCode]/10_CustomerSupplied | G19: Read: All members Write/Modify: PM, TL, Tester, Developer Delete: PM | H19: Teams
B20: =ROW()-6 -> 14 | C20: 11_PQA | F20: /[ProjectCode]/11_PQA | G20: Read: All members Write/Modify: PM, PQA Delete: PQA | H20: Teams
B22: 2. File/Document Configuration
B23: No | C23: File | D23: Folder Location | F23: File Name Format | G23: Template Path | H23: Note
B24: 1 | C24: Architecture Design | D24: /[Project Code]/03_Design/AD/v[x.y]/ | F24: NWS_[ProjectCode]_AD_v[x.y] | G24: /[Project Code]/07_Documentation/Templates/NWS_AD_v1.0 | H24: x: major version, y: minor version
B25: 2 | C25: Detail Design | D25: /[Project Code]/03_Design/DD/v[x.y]/ | F25: NWS_[ProjectCode]_[FunctionID]_DD_v[x.y] | G25: /[Project Code]/07_Documentation/Templates/NWS_DD_v1.0 | H25: x: major version, y: minor version
B26: 3 | C26: Test Case | D26: /[Project Code]/05_Testing/[Stage]/[FunctionID] | F26: NWS_[ProjectCode]_[FunctionID]_TestCase_v[x.y] | G26: /[Project Code]/07_Documentation/Templates/NWS_TestCase_v1.0 | H26: x: major version, y: minor version
B27: 4 | C27: Test Result | D27: /[Project Code]/05_Testing/[Stage]/[FunctionID] | F27: NWS_[ProjectCode]_[FunctionID]_TestResult_v[x.y] | G27: /[Project Code]/07_Documentation/Templates/NWS_TestResult_v1.0 | H27: x: major version, y: minor version
B28: 5 | C28: Test Report | D28: /[Project Code]/05_Testing/[Stage]/ | F28: NWS_[ProjectCode]_[Stage]_TestReport_v[x.y] | G28: /[Project Code]/07_Documentation/Templates/NWS_TestReport_v1.0 | H28: + Stage: UT/IT/ST/UAT
B29: 6 | C29: …
B30: 7
B32: 3. Source Code Management
B33: 3.1. Branch management
B34: No | C34: Branch | D34: Description | F34: Content Format | G34: Note
B35: 1 | C35: main | D35: chứa phiên bản stable đã release.
B36: 2 | C36: develop | D36: code tích hợp từ dev, chuẩn bị build. | F36: develop/[feature-id]
B37: 3 | C37: feature | D37: mỗi tính năng mới.
B38: 4 | C38: hotfix | D38: xử lý lỗi khẩn cấp.
B39: 5
B41: 3.2. Source code management (Pull request, code review & tagging)
B42: No | C42: Activity | D42: Description | F42: Content Format | G42: Note
B43: 1 | C43: Hệ thống quản lý mã nguồn | D43: GitLab / GitHub / Bitbucket
B44: 2 | C44: Nhánh chính | D44: main, develop, release/* (tùy Git flow)
B45: 3 | C45: Chiến lược nhánh | D45: Git Flow / Feature branching / Trunk-based
B46: 4 | C46: Quy trình Pull Request | D46: - Feature branch → Merge vào develop - Phải có ít nhất 1 code reviewer chấp thuận
B47: 5 | C47: Code Review Rules | D47: - Review theo checklist (naming, logic, performance...) - Không Merge nếu có comment chưa resolved
B48: 6 | C48: Tagging / Versioning | D48: - Theo Semantic Versioning: v1.0.0, v1.1.2 - Tag khi chuẩn bị release hoặc sau khi pass UAT
B49: 7
B50: 8
B51: 9
B52: 10
B54: 3.3. Source code's Build management
B55: No | C55: Activity | D55: Description | F55: Content Format | G55: Note
B56: 1 | C56: Công cụ build | D56: Maven / Gradle / npm / Webpack / Docker build…
B57: 2 | C57: Công cụ CI/CD | D57: GitLab CI, Jenkins, GitHub Actions…
B58: 3 | C58: Trigger build | D58: - Tự động khi push/Merge vào develop / main - Thủ công nếu là bản release
B59: 4 | C59: Quy trình build | D59: 1. Pull source → 2. Build → 3. Run tests → 4. Package artifact (ZIP, Docker image…)
B60: 5 | C60: Build environments | D60: dev / staging / production
B61: 6 | C61: Kiểm soát thất bại build | D61: Notify trên Slack / Email + Không cho phép merge nếu build fail
B63: 3.4. Source code's Deployment management
B64: No | C64: Activity | D64: Description | F64: Content Format | G64: Note
B65: 1 | C65: Môi trường triển khai | D65: - Dev: auto deploy từ develop - Staging: deploy từ bản build có tag release-* - Production: deploy thủ công / approve bởi PM
B66: 2 | C66: Công cụ triển khai | D66: - Docker Compose / Kubernetes / AWS ECS - Ansible / Terraform (nếu hạ tầng Tự động)
B67: 3 | C67: Chiến lược triển khai | D67: Rolling Update / Blue-Green / Canary
B68: 4 | C68: Tự động hay thủ công | D68: - Tự động: CI/CD pipeline deploy đến Dev - Thủ công: Prod deploy Phải có approval
B69: 5 | C69: Kế hoạch rollback | D69: - Giữ lại 2 bản gần nhất - Rollback bằng tag version hoặc backup
B70: 6 | C70: Quản lý biến môi trường | D70: - .env file, Secret Manager (AWS, Vault…) - Không commit biến nhạy cảm vào Git
B72: 4. Environement Control
B73: 4.1. Environment Control
B74: No | C74: Enviroment | D74: Description | F74: Location/IP | G74: Access Permission | H74: PIC
B75: 1 | C75: Development Environment | D75: Môi trường lập trình, chứa mã nguồn, dữ liệu giả, không quan trọng | F75: 192.168.10.10 / dev.local | G75: Chỉ Developer, không truy cập từ bên ngoài | H75: Nguyễn Văn A (Lead Developer)
B76: 2 | C76: Test Environment | D76: Môi trường kiểm thử tính năng, dữ liệu gần thật nhưng không nhạy cảm | F76: 192.168.20.20 / test.local | G76: Developer, Tester (QA), không cho khách hàng | H76: Trần Thị B (QA Leader)
B77: 3 | C77: Staging Environment | D77: Môi trường staging giả lập production, dùng kiểm tra cuối cùng | F77: 192.168.30.30 / staging.local | G77: PM, QA Leader, Dev Leader, kiểm soát chặt chẽ | H77: Lê Văn C (PM)
B78: 4 | C78: Production Environment | D78: Môi trường chính, chứa dữ liệu thật, dịch vụ đang chạy | F78: 203.113.xxx.xxx / prod.domain | G78: Chỉ SysAdmin, có 2FA, audit log đầy đủ | H78: Phạm Thị D (Infra Manager)
B80: 4.2. Environment Requirement
B81: No | C81: Enviroment | D81: Item | E81: Feature | F81: Description | G81: Environment Link
B82: 1 | C82: Development Environment | D82: Server | E82: OS | F82: Windows 10 x64
B83: 2 | E83: Database | F83: MySQL server 7.0
B84: 3 | E84: Development Language | F84: PHP: 7.4
B85: 4 | D85: Client | E85: OS | F85: Windows 10 x64
B86: 5 | D86: Mobile Device | E86: Mobile OS | F86: iOS xx.x
B87: 6 | D87: Browser | E87: Version | F87: Mobile: iPhone 14 Chrome 12.x, Safari 17.x
B88: 7 | C88: Test Environment | D88: Server | E88: OS | F88: Windows 10 x64
B89: 8 | E89: Database | F89: MySQL server 7.0
B90: 9 | E90: Development Language | F90: PHP: 7.4
B91: 10 | D91: Client | E91: OS | F91: Windows 10 x64
B92: 11 | D92: Mobile Device | E92: Mobile OS | F92: iOS xx.x
B93: 12 | D93: Browser | E93: Version | F93: Mobile: iPhone 14 Chrome 12.x, Safari 17.x
B94: 13 | C94: Staging Environment | D94: Server | E94: OS | F94: Windows 10 x64
B95: 14 | E95: Database | F95: MySQL server 7.0
B96: 15 | E96: Development Language | F96: PHP: 7.4
B97: 16 | D97: Client | E97: OS | F97: Windows 10 x64
B98: 17 | D98: Mobile Device | E98: Mobile OS | F98: iOS xx.x
B99: 18 | D99: Browser | E99: Version | F99: Mobile: iPhone 14 Chrome 12.x, Safari 17.x
B100: 19 | C100: Production Environment | D100: Server | E100: OS | F100: Windows 10 x64
B101: 20 | E101: Database | F101: MySQL server 7.0
B102: 21 | E102: Development Language | F102: PHP: 7.4
B103: 22 | D103: Client | E103: OS | F103: Windows 10 x64
B104: 23 | D104: Mobile Device | E104: Mobile OS | F104: iOS xx.x
B105: 24 | D105: Browser | E105: Version | F105: Mobile: iPhone 14 Chrome 12.x, Safari 17.x
B107: 5. Other Configuration
B108: No | C108: Item | D108: Description | F108: Standard Setting | G108: Note
B109: 1 | C109: Log Management | D109: Cấu hình hệ thống ghi log ứng dụng, hệ thống và audit log | F109: Log lưu 90 ngày, phân quyền truy cập log rõ ràng | G109: Phân biệt log application và OS
B110: 2 | C110: Time Synchronization (NTP) | D110: Đồng bộ thời gian hệ thống với NTP server | F110: Sử dụng NTP nội bộ hoặc ntp.vnpt.vn | G110: Quan trọng để kiểm tra log chính xác
...

Sheet 4. Communication Plan & Tools
D1: Communication Plan & Tools | H1: ='0. Tasklist'!$G$1 -> Mã số: BM03-QT-OP-01
H2: ='0. Tasklist'!$G$2 -> Ngày hiệu lực: 10/09/2025
H3: ='0. Tasklist'!$G$3 -> Lần ban hành: 02
B5: 1. Meeting Plan
B6: No | C6: Meeting Type | D6: Method | E6: Frequently | F6: Goal/Content | G6: Facilitator | H6: Time
B7: 1 | C7: Kick-off meeting | D7: Meeting | E7: Start Project | F7: TBD | G7: PM
B8: 2 | C8: Daily meeting | D8: Meeting | E8: Daily | F8: TBD | G8: PM
B9: 3 | C9: Daily report | D9: Chat (Teams) | E9: Daily | F9: TBD | G9: PM
B10: 4 | C10: Trao đổi nội bộ | D10: Chat (Teams) | E10: Real-time | F10: TBD | G10: Team
B11: 5 | C11: Grooming & Planing | D11: Meeting | E11: Start sprint | F11: TBD | G11: PM
B12: 6 | C12: Review & Retrospective | D12: Meeting | E12: End sprint | F12: TBD | G12: PM
B13: 7 | C13: Internal Demo | D13: Meeting | E13: End sprint | F13: TBD | G13: PM
B14: 8
B15: 9
B16: 10
B18: 2. Communication plan
B19: No | C19: Communication Type | D19: Method | E19: Frequently | F19: Goal/Content | G19: Facilitator | H19: Time
B20: 1 | C20: Weekly Report | D20: File | E20: Weekly | F20: TBD | G20: PM
B21: 2 | C21: Issue Report | D21: File | E21: Irregular, TBD | F21: TBD | G21: PM
B22: 3 | C22: Liên lạc | E22: Real-time | F22: TBD | G22: Team
B23: 4 | C23: Trao đổi Q&A | D23: Google Docs | E23: Real-time | F23: TBD | G23: Team
B24: 5
B25: 6
B26: 7
B27: 8
B28: 9
B29: 10
B31: 3. Comunication Tools
B32: No | C32: Tools | D32: Stage | E32: Purpose | G32: Version | H32: Security & Compliance requirements
B33: 1 | D33: All
B34: 2 | D34: All
B35: 3 | D35: All
B36: 4 | D36: All
B37: 5 | D37: All
B39: 4. Tools
B40: No | C40: Tools | D40: Stage | E40: Purpose | G40: Version | H40: Security & Compliance requirements
B41: 1 | D41: All
B42: 2 | D42: All
B43: 3 | D43: All
B44: 4 | D44: All
B45: 5 | D45: All

Sheet 5. Standard Metric
D1: Project Metric | H1: ='0. Tasklist'!$G$1 -> Mã số: BM03-QT-OP-01
H2: ='0. Tasklist'!$G$2 -> Ngày hiệu lực: 10/09/2025
H3: ='0. Tasklist'!$G$3 -> Lần ban hành: 02
B5: 1. Project Standard Metric
F6: Target | L6: Result tracking
B7: No | C7: Category | D7: Metric | E7: Unit | F7: LSL | G7: Average | H7: USL | I7: Objectives | J7: Formula | K7: When | L7: YYYY-MM-DD | M7: YYYY-MM-DD | N7: YYYY-MM-DD | O7: YYYY-MM-DD | P7: YYYY-MM-DD
B8: 1 | C8: Quality | D8: Customer Satisfaction | E8: Point | F8: 80 | G8: 90 | H8: 100 | I8: Đánh giá mức độ đáp ứng yêu cầu của khách hàng | J8: Tổng điểm trong phiếu khảo sát khách hàng từng lần/ kết thúc dự án | K8: Fixed Prices: Close Project Labo : 2 tuần/lần
B9: 2 | D9: Leakage | E9: No.Def/MM | F9: 0.06 | G9: 0.13 | H9: 0.2 | I9: Đo chất lượng sản phẩm/dịch vụ sau khi bàn giao (User Acceptance Test) | J9: – Số lỗi phát hiện sau bàn giao / Kích thước dự án | K9: End phase/ Close project
B10: 3 | D10: Defect rate (Coding) | E10: No.Def/MM | F10: 12 | G10: 17 | H10: 23 | I10: Đánh giá chất lượng toàn bộ sản phẩm dự án | J10: – Tổng số lỗi (Code review + Peer review+ Unit test)/ Kích thước dự án | K10: Fixed Prices: Milestone/End phase /Close project Labo: Monthly/End phase /Close project
B11: 4 | D11: Defect rate (Testing) | E11: No.Def/MM | F11: 3 | G11: 6.5 | H11: 9.7 | I11: Đánh giá chất lượng toàn bộ sản phẩm dự án | J11: – Tổng số lỗi (System Test + Integration Test + Regression Test) / Kích thước dự án | K11: Fixed Prices: Milestone/End phase /Close project Labo: Monthly/End phase /Close project
B12: 5 | C12: Cost | D12: Effort Efficiency | E12: % | F12: 80 | G12: 95 | H12: 110 | I12: Đo lường hiệu suất sử dụng nguồn lực dự án | J12: = (Plan MM / Actual effort ) * 100 | K12: Monthly/Close phase/Close project
B13: 6 | C13: Delivery | D13: Timeliness | E13: % | F13: 80 | G13: 90 | H13: 100 | I13: Đánh giá thời gian giao hàng đúng hạn | J13: = (Tổng thời gian giao đúng hạn / Tổng thời gian dự án cần giao tới khách hàng đến thời điểm báo cáo) × 100 | K13: Monthly/Close phase/Close project
B14: 7 | C14: Process | D14: Process Compliance | E14: % | F14: 80 | G14: 90 | H14: 100 | I14: Đánh giá mức độ tuân thủ chuẩn/quy trình/quy định | J14: = SUMPRODUCT(checked items,assessment results)/SUM(checked items). | K14: Labo: Monthly, Close phase/ project Fixed Prices: Milestone, Close phase/ project
B16: 2. Quality metric by Stage
F17: Target Result | L17: Result tracking
B18: No | C18: Stage | D18: Metric | E18: Description/ Calculation Formula | F18: Min value | G18: Norm value | H18: Max value | I18: Objectives | J18: Formula | K18: When | L18: YYYY-MM-DD | M18: YYYY-MM-DD | N18: YYYY-MM-DD | O18: YYYY-MM-DD | P18: YYYY-MM-DD
B19: 1 | C19: Architecture Design | D19: Comment rate for Basic Design | E19: Số comment/10 pages | F19: 2 | G19: 3 | H19: 5 | I19: Đánh giá mức độ đáp ứng yêu cầu của khách hàng cho tài liệu thiết kế kiến trúc | J19: Đếm tổng số comment được reviewer ghi chú trên tài liệu thiết kế cơ bản (Basic Design) chia theo số lượng trang (10 pages). 🔧 Tool: Word (Review → Comments), PDF Reader (Comment Summary), Google Docs (Comment Count) | K19: Fixed Prices: Milestone/End phase /Close project Labo: Monthly/End phase /Close project
B20: 2 | C20: Detail Design | D20: Comment rate for Detail Design | E20: Số comment/10 pages | F20: 3 | G20: 5 | H20: 7 | I20: Đánh giá mức độ đáp ứng yêu cầu của khách hàng cho tài liệu thiết kế chi tiết | J20: Tương tự như trên, nhưng áp dụng cho tài liệu thiết kế chi tiết (Detail Design). 🔧 Tool: Word, PDF, hoặc hệ thống DMS có lưu comment | K20: Fixed Prices: Milestone/End phase /Close project Labo: Monthly/End phase /Close project
B21: 3 | C21: Testing | D21: Bug rate for Unit Test | E21: Số comment hoặc lỗi/1000 dòng code | F21: 5 | G21: 10 | H21: 15 | I21: Đánh giá mức độ đáp ứng yêu cầu của khách hàng cho source code sau công đoạn coding | J21: Đếm số lỗi (bugs) được phát hiện trong Unit Test chia cho số lượng dòng code viết mới. 🔧 Tool: GitHub/GitLab + CLOC để tính LOC + Test result log | K21: Fixed Prices: Milestone/End phase /Close project Labo: Monthly/End phase /Close project
B22: 4 | C22: Testing | D22: Coverage rate for Unit test | E22: Tỉ lệ Coverage source code … | F22: 0.8 | G22: 0.9 | H22: 1 | I22: Đánh giá mức độ đáp ứng yêu cầu của khách hàng cho source code sau công đoạn coding | J22: Dùng công cụ đo coverage để tính số dòng code được test chia cho tổng số dòng code. 🔧 Tool: JUnit, NUnit | K22: Fixed Prices: Milestone/End phase /Close project Labo: Monthly/End phase /Close project
B23: 5 | C23: Testing | D23: Bug rate for IT Test | E23: Số bug/1000 dòng code | F23: 5 | G23: 7 | H23: 10 | I23: Đánh giá mức độ đáp ứng yêu cầu của khách hàng cho sản phẩm sau giai đoạn tích hợp hệ thống | J23: Tổng số lỗi được ghi nhận trong IT Test chia cho tổng số dòng code đôi tượng 🔧 Tool: Redmine, CLOC | K23: Fixed Prices: Milestone/End phase /Close project Labo: Monthly/End phase /Close project
B24: 6 | C24: Testing | D24: Bug rate for UAT Test | E24: Số bug/1000 dòng code | F24: 0.5 | G24: 0.7 | H24: 1 | I24: Đánh giá mức độ đáp ứng yêu cầu của khách hàng cho sản phẩm sau giai đoạn bàn giao hệ thống | J24: Tương tự trên nhưng tính lỗi trong quá trình UAT test. 🔧 Tool: Redmine, CLOC | K24: Fixed Prices: Milestone/End phase /Close project Labo: Monthly/End phase /Close project
B25: 7 | C25: Testing | D25: Bug rate for IT Test | E25: Số Bug/MM | F25: 15 | G25: 20 | H25: 25 | I25: Đánh giá mức độ đáp ứng yêu cầu của khách hàng cho sản phẩm sau giai đoạn tích hợp hệ thống | J25: Tổng số bug tìm thấy trong IT Test chia cho số MM (man-month) effort đã sử dụng. 🔧 Tool: Redmine + Resource allocation trên kênh PM | K25: Fixed Prices: Milestone/End phase /Close project Labo: Monthly/End phase /Close project
B26: 8 | C26: Testing | D26: Bug rate for UAT Test | E26: Số Bug/MM | F26: 3 | G26: 5 | H26: 7 | I26: Đánh giá mức độ đáp ứng yêu cầu của khách hàng cho sản phẩm sau giai đoạn bàn giao hệ thống | J26: Tổng số bug tìm thấy trong UAT Test chia cho số MM (man-month) effort đã sử dụng. 🔧 Tool: Redmine + Resource allocation trên kênh PM | K26: Fixed Prices: Milestone/End phase /Close project Labo: Monthly/End phase /Close project
B28: 3. Quality Assurance Strategic
B29: No | C29: Stage | D29: Activity | E29: Approach Method | F29: Description
B30: 1 | C30: Coding | D30: Coding | E30: Triển khai áp dụng tiêu chuẩn coding chuẩn | F30: Áp dụng chuẩn (ví dụ: Google Java Style, JavaScript Style Guide). Có file .editorconfig để thống nhất format.
B31: 2 | C31: Coding | D31: Code review | E31: Triển khai chạy review static source code dùng tool | F31: Chạy tự động SonarQube, ESLint khi commit/push. Rule: Cyclomatic Complexity, Code Smells, Security Vulnerabilities. Threshold: Code Smells < X, Coverage ≥ 80%.
B32: 3 | C32: Coding | D32: Code review | E32: Triển khai Leader thực hiện review code | F32: Pull Request/Checklist review bắt buộc Tối thiểu có 1 lượt cross review hoặc leader review Bắt buộc sửa comment trước khi merge Comment list tổng hợp lại trên redmine
B33: 4 | C33: Testing | D33: Unit test | E33: Triển khai thiết lập tiêu chuẩn Unit testing | F33: Tối thiểu đến cover C0/C1. Gồm cả abnormal case
B34: 5 | C34: Testing | D34: Unit test | E34: Triển khai tiêu chuẩn execute Unit testing | F34: Coverage ≥ 80% Unit Test phải chạy tự động qua CI/CD pipeline.
B35: 6 | C35: Testing | D35: Integration Test | E35: Triển khai phân tích nguyên nhân bug theo phương pháp 5Why | F35: Phân tích nguyên nhân, dùng 5Why để tìm được nguyên nhân gốc rễ Đưa ra solution Check similar Check degrade Đối ứng toàn bộ các similar và degrade
B38: 4. Non-functional requirements ensuring criteria
B39: (*)Trong trường hợp khách hàng yêu cầu
B40: No | C40: Stage | D40: Activity | E40: Approach Method | F40: Description
B41: 1 | C41: Coding | D41: Coding | E41: Performance | F41: Áp dụng các kỹ thuật cải thiện performance như : + Đánh index + Dùng store procedure + Multi-thread + Review luồng nghiệp vụ tổng quan

Sheet 6. Other plan
D1: Change Management & Risk management​ | H1: ='0. Tasklist'!$G$1 -> Mã số: BM03-QT-OP-01
H2: ='0. Tasklist'!$G$2 -> Ngày hiệu lực: 10/09/2025
H3: ='0. Tasklist'!$G$3 -> Lần ban hành: 02
B5: 1. Change Management Plan
B6: No | C6: Item | D6: Description | F6: Note
B7: 1 | C7: Change Management File | D7: Refer [BM06_NWS_[ProjectCode]_CR Management_v1.0]
B9: 2. Risk Management​ Plan
B10: No | C10: Management​ content | D10: Description | F10: Note
B11: 1 | C11: Risk Management File | D11: Refer [BM04_NWS_[ProjectCode]_Risk Management_v1.0]
B13: 3. Resource Allocation Plan
B14: No | C14: Management​ content | D14: Description | F14: Note
B15: 1 | C15: Resource Allocation File | D15: Refer [BM12_NWS_[ProjectCode]_Resource Allocation Plan_v1.0]

Sheet Master
A1: Master Data
A2: Resposibility
A3: No | B3: Item | C3: Description | E3: No | F3: Stage
A4: 1 | B4: R | C4: Responsible (Does the work) | E4: 1 | F4: Requirement Gathering
A5: 2 | B5: A | C5: Accountable (Final approval) | E5: 2 | F5: System Analysis
A6: 3 | B6: C | C6: Consulted (Provides input) | E6: 3 | F6: UI/UX Design
A7: 4 | B7: I | C7: Informed (Kept updated) | E7: 4 | F7: Architecture Design
A8: 5 | B8: - | C8: None | E8: 5 | F8: Detail Design
E9: 6 | F9: Coding
E10: 7 | F10: Testing
E11: 8 | F11: Deployment
E12: 9 | F12: Maintenance
E13: 10 | F13: All
